rnaernie/__init__.py
rnaernie/inference.py
rnaernie/init_model.py
rnaernie/test.py
rnaernie/test_plt.py
rnaernie/train.py
rnaernie/src/__init__.py
rnaernie/src/data/__init__.py
rnaernie/src/data/collator.py
rnaernie/src/data/loader.py
rnaernie/src/data/parser.py
rnaernie/src/data/preprocess.py
rnaernie/src/extras/__init__.py
rnaernie/src/extras/callbacks.py
rnaernie/src/extras/constants.py
rnaernie/src/extras/logging.py
rnaernie/src/extras/misc.py
rnaernie/src/extras/ploting.py
rnaernie/src/hparams/__init__.py
rnaernie/src/hparams/data_args.py
rnaernie/src/hparams/inference_args.py
rnaernie/src/hparams/model_args.py
rnaernie/src/hparams/parser.py
rnaernie/src/hparams/pretraining_args.py
rnaernie/src/hparams/stage_args.py
rnaernie/src/models/__init__.py
rnaernie/src/models/loader.py
rnaernie/src/models/patcher.py
rnaernie/src/models/tokenization_utils.py
rnaernie/src/models/rnaernie/__init__.py
rnaernie/src/models/rnaernie/tokenization_rnaernie.py
rnaernie/src/pipeline/__init__.py
rnaernie/src/pipeline/tuner.py
rnaernie/src/pipeline/utils.py
rnaernie/src/pipeline/infer/__init__.py
rnaernie/src/pipeline/infer/inferencer.py
rnaernie/src/pipeline/infer/workflow.py
rnaernie/src/pipeline/pt/__init__.py
rnaernie/src/pipeline/pt/trainer.py
rnaernie/src/pipeline/pt/workflow.py
rnaernie-0.1.5.dist-info/METADATA
rnaernie-0.1.5.dist-info/WHEEL
rnaernie-0.1.5.dist-info/top_level.txt
rnaernie-0.1.5.dist-info/RECORD
