Metadata-Version: 2.1
Name: rnaernie
Version: 0.1.5
Summary: RNAErnie2
Home-page: https://github.com/CatIIIIIIII/RNAErnie2
Author: WANG Ning
Author-email: wangning.roci@gmail.com
License: MIT
Classifier: Programming Language :: Python :: 3
Classifier: License :: OSI Approved :: MIT License
Classifier: Operating System :: OS Independent
Requires-Python: >=3.6
